__init__.py
filmot/__init__.py
filmot/asyncit.py
filmot/config.py
filmot/consts.py
filmot/dicts.py
filmot/exceptions.py
filmot/filmot.py
filmot/responses.py
filmot/responses_base.py
filmot-0.0.4.dist-info/LICENSE
filmot-0.0.4.dist-info/METADATA
filmot-0.0.4.dist-info/WHEEL
filmot-0.0.4.dist-info/top_level.txt
filmot-0.0.4.dist-info/RECORD
